pk_prob_distributions
