Metadata-Version: 2.1
Name: pk-prob-distributions
Version: 0.3
Summary: Gaussian and Binomial distributions
Home-page: UNKNOWN
Author: Alexander Romero
Author-email: alexander.romerobiz@gmail.com
License: UNKNOWN
Platform: UNKNOWN
